pyax25_22/__init__.py
pyax25_22/core/__init__.py
pyax25_22/core/config.py
pyax25_22/core/connected.py
pyax25_22/core/exceptions.py
pyax25_22/core/flow_control.py
pyax25_22/core/framing.py
pyax25_22/core/negotiation.py
pyax25_22/core/statemachine.py
pyax25_22/core/timers.py
pyax25_22/core/validation.py
pyax25_22/interfaces/__init__.py
pyax25_22/interfaces/agwpe.py
pyax25_22/interfaces/kiss.py
pyax25_22/interfaces/transport.py
pyax25_22/utils/logging.py
pyax25_22-0.5.97.dist-info/licenses/LICENSE
pyax25_22-0.5.97.dist-info/METADATA
pyax25_22-0.5.97.dist-info/WHEEL
pyax25_22-0.5.97.dist-info/top_level.txt
pyax25_22-0.5.97.dist-info/RECORD
