Metadata-Version: 2.4
Name: pyax25-22
Version: 0.5.97
Summary: Pure Python implementation of AX.25 v2.2 Layer 2 protocol for amateur radio
Home-page: https://github.com/ke4ahr/PyAX25_22
Author: Kris Kirby, KE4AHR
License: LGPL-3.0-or-later
Project-URL: Homepage, https://github.com/ke4ahr/PyAX25_22
Project-URL: Documentation, https://github.com/ke4ahr/PyAX25_22/tree/main/docs
Project-URL: Bug Tracker, https://github.com/ke4ahr/PyAX25_22/issues
Project-URL: Source Code, https://github.com/ke4ahr/PyAX25_22
Keywords: ax25,packet-radio,amateur-radio,ham-radio,kiss,agwpe,tnc,pacsat,aprs
Classifier: Programming Language :: Python :: 3
Classifier: Programming Language :: Python :: 3.8
Classifier: Programming Language :: Python :: 3.9
Classifier: Programming Language :: Python :: 3.10
Classifier: Programming Language :: Python :: 3.11
Classifier: Programming Language :: Python :: 3.12
Classifier: License :: OSI Approved :: GNU Lesser General Public License v3 or later (LGPLv3+)
Classifier: Operating System :: OS Independent
Classifier: Topic :: Communications :: Ham Radio
Classifier: Topic :: Software Development :: Libraries :: Python Modules
Classifier: Intended Audience :: Developers
Classifier: Development Status :: 4 - Beta
Requires-Python: >=3.8
License-File: LICENSE
Requires-Dist: pyserial>=3.5
Provides-Extra: async
Requires-Dist: aiohttp>=3.8; extra == "async"
Provides-Extra: dev
Requires-Dist: pytest>=7.0; extra == "dev"
Requires-Dist: pytest-cov>=4.0; extra == "dev"
Requires-Dist: black>=24.0; extra == "dev"
Requires-Dist: ruff>=0.1.0; extra == "dev"
Requires-Dist: mypy>=1.0; extra == "dev"
Requires-Dist: sphinx>=7.0; extra == "dev"
Requires-Dist: sphinx-rtd-theme>=2.0; extra == "dev"
Dynamic: home-page
Dynamic: license-file
Dynamic: requires-python
